setup.py
src/bc_acc_dup/__init__.py
src/bc_acc_dup/__main__.py
src/bc_acc_dup/adb_handler.py
src/bc_acc_dup/config_manager.py
src/bc_acc_dup/csv_handler.py
src/bc_acc_dup/feature_handler.py
src/bc_acc_dup/game_data_getter.py
src/bc_acc_dup/helper.py
src/bc_acc_dup/item.py
src/bc_acc_dup/locale_handler.py
src/bc_acc_dup/managed_item.py
src/bc_acc_dup/parse_save.py
src/bc_acc_dup/patcher.py
src/bc_acc_dup/py.typed
src/bc_acc_dup/root_handler.py
src/bc_acc_dup/serialise_save.py
src/bc_acc_dup/server_handler.py
src/bc_acc_dup/tracker.py
src/bc_acc_dup/updater.py
src/bc_acc_dup/user_input_handler.py
src/bc_acc_dup/edits/__init__.py
src/bc_acc_dup/edits/basic/__init__.py
src/bc_acc_dup/edits/basic/basic_items.py
src/bc_acc_dup/edits/basic/catfruit.py
src/bc_acc_dup/edits/basic/catseyes.py
src/bc_acc_dup/edits/basic/ototo_base_mats.py
src/bc_acc_dup/edits/basic/talent_orbs.py
src/bc_acc_dup/edits/basic/talent_orbs_new.py
src/bc_acc_dup/edits/cats/__init__.py
src/bc_acc_dup/edits/cats/cat_helper.py
src/bc_acc_dup/edits/cats/cat_id_selector.py
src/bc_acc_dup/edits/cats/chara_drop.py
src/bc_acc_dup/edits/cats/clear_cat_guide.py
src/bc_acc_dup/edits/cats/evolve_cats.py
src/bc_acc_dup/edits/cats/get_remove_cats.py
src/bc_acc_dup/edits/cats/talents.py
src/bc_acc_dup/edits/cats/upgrade_blue.py
src/bc_acc_dup/edits/cats/upgrade_cats.py
src/bc_acc_dup/edits/gamototo/__init__.py
src/bc_acc_dup/edits/gamototo/fix_gamatoto.py
src/bc_acc_dup/edits/gamototo/gamatoto_xp.py
src/bc_acc_dup/edits/gamototo/helpers.py
src/bc_acc_dup/edits/gamototo/ototo_cat_cannon.py
src/bc_acc_dup/edits/levels/__init__.py
src/bc_acc_dup/edits/levels/aku.py
src/bc_acc_dup/edits/levels/allow_filibuster_clearing.py
src/bc_acc_dup/edits/levels/behemoth_culling.py
src/bc_acc_dup/edits/levels/clear_tutorial.py
src/bc_acc_dup/edits/levels/enigma_stages.py
src/bc_acc_dup/edits/levels/event_stages.py
src/bc_acc_dup/edits/levels/gauntlet.py
src/bc_acc_dup/edits/levels/itf_timed_scores.py
src/bcdup.egg-info/PKG-INFO
src/bcdup.egg-info/SOURCES.txt
src/bcdup.egg-info/dependency_links.txt
src/bcdup.egg-info/requires.txt
src/bcdup.egg-info/top_level.txt