Metadata-Version: 2.1
Name: bcdup
Version: 2.3.2
Summary: BCSFE_Python personal api
Home-page: UNKNOWN
Author: CintagramABP
License: UNKNOWN
Platform: UNKNOWN
Requires-Python: >=3.9
Provides-Extra: testing
